Compiled from "MilvusEmbeddingStore.java"
public class dev.langchain4j.store.embedding.milvus.MilvusEmbeddingStore implements dev.langchain4j.store.embedding.EmbeddingStore<dev.langchain4j.data.segment.TextSegment> {
  private static final java.lang.String DEFAULT_ID_FIELD_NAME;

  private static final java.lang.String DEFAULT_TEXT_FIELD_NAME;

  private static final java.lang.String DEFAULT_METADATA_FIELD_NAME;

  private static final java.lang.String DEFAULT_VECTOR_FIELD_NAME;

  private final io.milvus.client.MilvusServiceClient milvusClient;

  private final java.lang.String collectionName;

  private final io.milvus.param.MetricType metricType;

  private final io.milvus.common.clientenum.ConsistencyLevelEnum consistencyLevel;

  private final boolean retrieveEmbeddingsOnSearch;

  private final boolean autoFlushOnInsert;

  private final dev.langchain4j.store.embedding.milvus.FieldDefinition fieldDefinition;

  public dev.langchain4j.store.embedding.milvus.MilvusEmbeddingStore(java.lang.String, java.lang.Integer, java.lang.String, java.lang.Integer, io.milvus.param.IndexType, io.milvus.param.MetricType, java.lang.String, java.lang.String, java.lang.String, java.lang.String, io.milvus.common.clientenum.ConsistencyLevelEnum, java.lang.Boolean, java.lang.Boolean, java.lang.String, java.lang.String, java.lang.String, java.lang.String, java.lang.String);
    Code:
       0: aload_0
       1: aload_1
       2: aload_2
       3: aload         7
       5: aload         8
       7: aload         9
       9: aload         10
      11: aload         14
      13: invokestatic  #1                  // Method createMilvusClient:(Ljava/lang/String;Ljava/lang/Integer;Ljava/lang/String;Ljava/lang/String;Ljava/lang/String;Ljava/lang/String;Ljava/lang/String;)Lio/milvus/client/MilvusServiceClient;
      16: aload_3
      17: aload         4
      19: aload         5
      21: aload         6
      23: aload         11
      25: aload         12
      27: aload         13
      29: aload         15
      31: aload         16
      33: aload         17
      35: aload         18
      37: invokespecial #7                  // Method "<init>":(Lio/milvus/client/MilvusServiceClient;Ljava/lang/String;Ljava/lang/Integer;Lio/milvus/param/IndexType;Lio/milvus/param/MetricType;Lio/milvus/common/clientenum/ConsistencyLevelEnum;Ljava/lang/Boolean;Ljava/lang/Boolean;Ljava/lang/String;Ljava/lang/String;Ljava/lang/String;Ljava/lang/String;)V
      40: return

  public dev.langchain4j.store.embedding.milvus.MilvusEmbeddingStore(io.milvus.client.MilvusServiceClient, java.lang.String, java.lang.Integer, io.milvus.param.IndexType, io.milvus.param.MetricType, io.milvus.common.clientenum.ConsistencyLevelEnum, java.lang.Boolean, java.lang.Boolean, java.lang.String, java.lang.String, java.lang.String, java.lang.String);
    Code:
       0: aload_0
       1: invokespecial #11                 // Method java/lang/Object."<init>":()V
       4: aload_0
       5: aload_1
       6: ldc           #16                 // String milvusClient
       8: invokestatic  #18                 // Method dev/langchain4j/internal/ValidationUtils.ensureNotNull:(Ljava/lang/Object;Ljava/lang/String;)Ljava/lang/Object;
      11: checkcast     #24                 // class io/milvus/client/MilvusServiceClient
      14: putfield      #26                 // Field milvusClient:Lio/milvus/client/MilvusServiceClient;
      17: aload_0
      18: aload_2
      19: ldc           #29                 // String default
      21: invokestatic  #31                 // Method dev/langchain4j/internal/Utils.getOrDefault:(Ljava/lang/Object;Ljava/lang/Object;)Ljava/lang/Object;
      24: checkcast     #37                 // class java/lang/String
      27: putfield      #39                 // Field collectionName:Ljava/lang/String;
      30: aload_0
      31: aload         5
      33: getstatic     #43                 // Field io/milvus/param/MetricType.COSINE:Lio/milvus/param/MetricType;
      36: invokestatic  #31                 // Method dev/langchain4j/internal/Utils.getOrDefault:(Ljava/lang/Object;Ljava/lang/Object;)Ljava/lang/Object;
      39: checkcast     #44                 // class io/milvus/param/MetricType
      42: putfield      #49                 // Field metricType:Lio/milvus/param/MetricType;
      45: aload_0
      46: aload         6
      48: getstatic     #52                 // Field io/milvus/common/clientenum/ConsistencyLevelEnum.EVENTUALLY:Lio/milvus/common/clientenum/ConsistencyLevelEnum;
      51: invokestatic  #31                 // Method dev/langchain4j/internal/Utils.getOrDefault:(Ljava/lang/Object;Ljava/lang/Object;)Ljava/lang/Object;
      54: checkcast     #53                 // class io/milvus/common/clientenum/ConsistencyLevelEnum
      57: putfield      #58                 // Field consistencyLevel:Lio/milvus/common/clientenum/ConsistencyLevelEnum;
      60: aload_0
      61: aload         7
      63: iconst_0
      64: invokestatic  #61                 // Method java/lang/Boolean.valueOf:(Z)Ljava/lang/Boolean;
      67: invokestatic  #31                 // Method dev/langchain4j/internal/Utils.getOrDefault:(Ljava/lang/Object;Ljava/lang/Object;)Ljava/lang/Object;
      70: checkcast     #62                 // class java/lang/Boolean
      73: invokevirtual #67                 // Method java/lang/Boolean.booleanValue:()Z
      76: putfield      #71                 // Field retrieveEmbeddingsOnSearch:Z
      79: aload_0
      80: aload         8
      82: iconst_0
      83: invokestatic  #61                 // Method java/lang/Boolean.valueOf:(Z)Ljava/lang/Boolean;
      86: invokestatic  #31                 // Method dev/langchain4j/internal/Utils.getOrDefault:(Ljava/lang/Object;Ljava/lang/Object;)Ljava/lang/Object;
      89: checkcast     #62                 // class java/lang/Boolean
      92: invokevirtual #67                 // Method java/lang/Boolean.booleanValue:()Z
      95: putfield      #75                 // Field autoFlushOnInsert:Z
      98: aload_0
      99: new           #78                 // class dev/langchain4j/store/embedding/milvus/FieldDefinition
     102: dup
     103: aload         9
     105: ldc           #80                 // String id
     107: invokestatic  #31                 // Method dev/langchain4j/internal/Utils.getOrDefault:(Ljava/lang/Object;Ljava/lang/Object;)Ljava/lang/Object;
     110: checkcast     #37                 // class java/lang/String
     113: aload         10
     115: ldc           #82                 // String text
     117: invokestatic  #31                 // Method dev/langchain4j/internal/Utils.getOrDefault:(Ljava/lang/Object;Ljava/lang/Object;)Ljava/lang/Object;
     120: checkcast     #37                 // class java/lang/String
     123: aload         11
     125: ldc           #84                 // String metadata
     127: invokestatic  #31                 // Method dev/langchain4j/internal/Utils.getOrDefault:(Ljava/lang/Object;Ljava/lang/Object;)Ljava/lang/Object;
     130: checkcast     #37                 // class java/lang/String
     133: aload         12
     135: ldc           #86                 // String vector
     137: invokestatic  #31                 // Method dev/langchain4j/internal/Utils.getOrDefault:(Ljava/lang/Object;Ljava/lang/Object;)Ljava/lang/Object;
     140: checkcast     #37                 // class java/lang/String
     143: invokespecial #88                 // Method dev/langchain4j/store/embedding/milvus/FieldDefinition."<init>":(Ljava/lang/String;Ljava/lang/String;Ljava/lang/String;Ljava/lang/String;)V
     146: putfield      #91                 // Field fieldDefinition:Ldev/langchain4j/store/embedding/milvus/FieldDefinition;
     149: aload_0
     150: getfield      #26                 // Field milvusClient:Lio/milvus/client/MilvusServiceClient;
     153: aload_0
     154: getfield      #39                 // Field collectionName:Ljava/lang/String;
     157: invokestatic  #95                 // Method dev/langchain4j/store/embedding/milvus/CollectionOperationsExecutor.hasCollection:(Lio/milvus/client/MilvusServiceClient;Ljava/lang/String;)Z
     160: ifne          223
     163: aload_0
     164: getfield      #26                 // Field milvusClient:Lio/milvus/client/MilvusServiceClient;
     167: aload_0
     168: getfield      #39                 // Field collectionName:Ljava/lang/String;
     171: aload_0
     172: getfield      #91                 // Field fieldDefinition:Ldev/langchain4j/store/embedding/milvus/FieldDefinition;
     175: aload_3
     176: ldc           #101                // String dimension
     178: invokestatic  #18                 // Method dev/langchain4j/internal/ValidationUtils.ensureNotNull:(Ljava/lang/Object;Ljava/lang/String;)Ljava/lang/Object;
     181: checkcast     #103                // class java/lang/Integer
     184: invokevirtual #105                // Method java/lang/Integer.intValue:()I
     187: invokestatic  #109                // Method dev/langchain4j/store/embedding/milvus/CollectionOperationsExecutor.createCollection:(Lio/milvus/client/MilvusServiceClient;Ljava/lang/String;Ldev/langchain4j/store/embedding/milvus/FieldDefinition;I)V
     190: aload_0
     191: getfield      #26                 // Field milvusClient:Lio/milvus/client/MilvusServiceClient;
     194: aload_0
     195: getfield      #39                 // Field collectionName:Ljava/lang/String;
     198: aload_0
     199: getfield      #91                 // Field fieldDefinition:Ldev/langchain4j/store/embedding/milvus/FieldDefinition;
     202: invokevirtual #113                // Method dev/langchain4j/store/embedding/milvus/FieldDefinition.getVectorFieldName:()Ljava/lang/String;
     205: aload         4
     207: getstatic     #117                // Field io/milvus/param/IndexType.FLAT:Lio/milvus/param/IndexType;
     210: invokestatic  #31                 // Method dev/langchain4j/internal/Utils.getOrDefault:(Ljava/lang/Object;Ljava/lang/Object;)Ljava/lang/Object;
     213: checkcast     #118                // class io/milvus/param/IndexType
     216: aload_0
     217: getfield      #49                 // Field metricType:Lio/milvus/param/MetricType;
     220: invokestatic  #123                // Method dev/langchain4j/store/embedding/milvus/CollectionOperationsExecutor.createIndex:(Lio/milvus/client/MilvusServiceClient;Ljava/lang/String;Ljava/lang/String;Lio/milvus/param/IndexType;Lio/milvus/param/MetricType;)V
     223: aload_0
     224: getfield      #26                 // Field milvusClient:Lio/milvus/client/MilvusServiceClient;
     227: aload_2
     228: invokestatic  #127                // Method dev/langchain4j/store/embedding/milvus/CollectionOperationsExecutor.loadCollectionInMemory:(Lio/milvus/client/MilvusServiceClient;Ljava/lang/String;)V
     231: return

  private static io.milvus.client.MilvusServiceClient createMilvusClient(java.lang.String, java.lang.Integer, java.lang.String, java.lang.String, java.lang.String, java.lang.String, java.lang.String);
    Code:
       0: invokestatic  #131                // Method io/milvus/param/ConnectParam.newBuilder:()Lio/milvus/param/ConnectParam$Builder;
       3: aload_0
       4: ldc           #137                // String localhost
       6: invokestatic  #31                 // Method dev/langchain4j/internal/Utils.getOrDefault:(Ljava/lang/Object;Ljava/lang/Object;)Ljava/lang/Object;
       9: checkcast     #37                 // class java/lang/String
      12: invokevirtual #139                // Method io/milvus/param/ConnectParam$Builder.withHost:(Ljava/lang/String;)Lio/milvus/param/ConnectParam$Builder;
      15: aload_1
      16: sipush        19530
      19: invokestatic  #145                // Method java/lang/Integer.valueOf:(I)Ljava/lang/Integer;
      22: invokestatic  #31                 // Method dev/langchain4j/internal/Utils.getOrDefault:(Ljava/lang/Object;Ljava/lang/Object;)Ljava/lang/Object;
      25: checkcast     #103                // class java/lang/Integer
      28: invokevirtual #105                // Method java/lang/Integer.intValue:()I
      31: invokevirtual #148                // Method io/milvus/param/ConnectParam$Builder.withPort:(I)Lio/milvus/param/ConnectParam$Builder;
      34: aload_2
      35: invokevirtual #152                // Method io/milvus/param/ConnectParam$Builder.withUri:(Ljava/lang/String;)Lio/milvus/param/ConnectParam$Builder;
      38: aload_3
      39: invokevirtual #155                // Method io/milvus/param/ConnectParam$Builder.withToken:(Ljava/lang/String;)Lio/milvus/param/ConnectParam$Builder;
      42: aload         4
      44: ldc           #158                // String
      46: invokestatic  #31                 // Method dev/langchain4j/internal/Utils.getOrDefault:(Ljava/lang/Object;Ljava/lang/Object;)Ljava/lang/Object;
      49: checkcast     #37                 // class java/lang/String
      52: aload         5
      54: ldc           #158                // String
      56: invokestatic  #31                 // Method dev/langchain4j/internal/Utils.getOrDefault:(Ljava/lang/Object;Ljava/lang/Object;)Ljava/lang/Object;
      59: checkcast     #37                 // class java/lang/String
      62: invokevirtual #160                // Method io/milvus/param/ConnectParam$Builder.withAuthorization:(Ljava/lang/String;Ljava/lang/String;)Lio/milvus/param/ConnectParam$Builder;
      65: astore        7
      67: aload         6
      69: ifnull        80
      72: aload         7
      74: aload         6
      76: invokevirtual #164                // Method io/milvus/param/ConnectParam$Builder.withDatabaseName:(Ljava/lang/String;)Lio/milvus/param/ConnectParam$Builder;
      79: pop
      80: new           #24                 // class io/milvus/client/MilvusServiceClient
      83: dup
      84: aload         7
      86: invokevirtual #167                // Method io/milvus/param/ConnectParam$Builder.build:()Lio/milvus/param/ConnectParam;
      89: invokespecial #171                // Method io/milvus/client/MilvusServiceClient."<init>":(Lio/milvus/param/ConnectParam;)V
      92: areturn

  public static dev.langchain4j.store.embedding.milvus.MilvusEmbeddingStore$Builder builder();
    Code:
       0: new           #174                // class dev/langchain4j/store/embedding/milvus/MilvusEmbeddingStore$Builder
       3: dup
       4: invokespecial #176                // Method dev/langchain4j/store/embedding/milvus/MilvusEmbeddingStore$Builder."<init>":()V
       7: areturn

  public void dropCollection(java.lang.String);
    Code:
       0: aload_0
       1: getfield      #26                 // Field milvusClient:Lio/milvus/client/MilvusServiceClient;
       4: aload_1
       5: invokestatic  #177                // Method dev/langchain4j/store/embedding/milvus/CollectionOperationsExecutor.dropCollection:(Lio/milvus/client/MilvusServiceClient;Ljava/lang/String;)V
       8: return

  public java.lang.String add(dev.langchain4j.data.embedding.Embedding);
    Code:
       0: invokestatic  #180                // Method dev/langchain4j/internal/Utils.randomUUID:()Ljava/lang/String;
       3: astore_2
       4: aload_0
       5: aload_2
       6: aload_1
       7: invokevirtual #183                // Method add:(Ljava/lang/String;Ldev/langchain4j/data/embedding/Embedding;)V
      10: aload_2
      11: areturn

  public void add(java.lang.String, dev.langchain4j.data.embedding.Embedding);
    Code:
       0: aload_0
       1: aload_1
       2: aload_2
       3: aconst_null
       4: invokevirtual #187                // Method addInternal:(Ljava/lang/String;Ldev/langchain4j/data/embedding/Embedding;Ldev/langchain4j/data/segment/TextSegment;)V
       7: return

  public java.lang.String add(dev.langchain4j.data.embedding.Embedding, dev.langchain4j.data.segment.TextSegment);
    Code:
       0: invokestatic  #180                // Method dev/langchain4j/internal/Utils.randomUUID:()Ljava/lang/String;
       3: astore_3
       4: aload_0
       5: aload_3
       6: aload_1
       7: aload_2
       8: invokevirtual #187                // Method addInternal:(Ljava/lang/String;Ldev/langchain4j/data/embedding/Embedding;Ldev/langchain4j/data/segment/TextSegment;)V
      11: aload_3
      12: areturn

  public java.util.List<java.lang.String> addAll(java.util.List<dev.langchain4j.data.embedding.Embedding>);
    Code:
       0: aload_1
       1: invokeinterface #191,  1          // InterfaceMethod java/util/List.size:()I
       6: invokestatic  #196                // Method dev/langchain4j/store/embedding/milvus/Generator.generateRandomIds:(I)Ljava/util/List;
       9: astore_2
      10: aload_0
      11: aload_2
      12: aload_1
      13: aconst_null
      14: invokevirtual #202                // Method addAll:(Ljava/util/List;Ljava/util/List;Ljava/util/List;)V
      17: aload_2
      18: areturn

  public dev.langchain4j.store.embedding.EmbeddingSearchResult<dev.langchain4j.data.segment.TextSegment> search(dev.langchain4j.store.embedding.EmbeddingSearchRequest);
    Code:
       0: aload_0
       1: getfield      #39                 // Field collectionName:Ljava/lang/String;
       4: aload_0
       5: getfield      #91                 // Field fieldDefinition:Ldev/langchain4j/store/embedding/milvus/FieldDefinition;
       8: aload_1
       9: invokevirtual #206                // Method dev/langchain4j/store/embedding/EmbeddingSearchRequest.queryEmbedding:()Ldev/langchain4j/data/embedding/Embedding;
      12: invokevirtual #212                // Method dev/langchain4j/data/embedding/Embedding.vectorAsList:()Ljava/util/List;
      15: aload_1
      16: invokevirtual #218                // Method dev/langchain4j/store/embedding/EmbeddingSearchRequest.filter:()Ldev/langchain4j/store/embedding/filter/Filter;
      19: aload_1
      20: invokevirtual #222                // Method dev/langchain4j/store/embedding/EmbeddingSearchRequest.maxResults:()I
      23: aload_0
      24: getfield      #49                 // Field metricType:Lio/milvus/param/MetricType;
      27: aload_0
      28: getfield      #58                 // Field consistencyLevel:Lio/milvus/common/clientenum/ConsistencyLevelEnum;
      31: invokestatic  #225                // Method dev/langchain4j/store/embedding/milvus/CollectionRequestBuilder.buildSearchRequest:(Ljava/lang/String;Ldev/langchain4j/store/embedding/milvus/FieldDefinition;Ljava/util/List;Ldev/langchain4j/store/embedding/filter/Filter;ILio/milvus/param/MetricType;Lio/milvus/common/clientenum/ConsistencyLevelEnum;)Lio/milvus/param/dml/SearchParam;
      34: astore_2
      35: aload_0
      36: getfield      #26                 // Field milvusClient:Lio/milvus/client/MilvusServiceClient;
      39: aload_2
      40: invokestatic  #231                // Method dev/langchain4j/store/embedding/milvus/CollectionOperationsExecutor.search:(Lio/milvus/client/MilvusServiceClient;Lio/milvus/param/dml/SearchParam;)Lio/milvus/response/SearchResultsWrapper;
      43: astore_3
      44: aload_0
      45: getfield      #26                 // Field milvusClient:Lio/milvus/client/MilvusServiceClient;
      48: aload_3
      49: aload_0
      50: getfield      #39                 // Field collectionName:Ljava/lang/String;
      53: aload_0
      54: getfield      #91                 // Field fieldDefinition:Ldev/langchain4j/store/embedding/milvus/FieldDefinition;
      57: aload_0
      58: getfield      #58                 // Field consistencyLevel:Lio/milvus/common/clientenum/ConsistencyLevelEnum;
      61: aload_0
      62: getfield      #71                 // Field retrieveEmbeddingsOnSearch:Z
      65: invokestatic  #235                // Method dev/langchain4j/store/embedding/milvus/Mapper.toEmbeddingMatches:(Lio/milvus/client/MilvusServiceClient;Lio/milvus/response/SearchResultsWrapper;Ljava/lang/String;Ldev/langchain4j/store/embedding/milvus/FieldDefinition;Lio/milvus/common/clientenum/ConsistencyLevelEnum;Z)Ljava/util/List;
      68: astore        4
      70: aload         4
      72: invokeinterface #241,  1          // InterfaceMethod java/util/List.stream:()Ljava/util/stream/Stream;
      77: aload_1
      78: invokedynamic #245,  0            // InvokeDynamic #0:test:(Ldev/langchain4j/store/embedding/EmbeddingSearchRequest;)Ljava/util/function/Predicate;
      83: invokeinterface #249,  2          // InterfaceMethod java/util/stream/Stream.filter:(Ljava/util/function/Predicate;)Ljava/util/stream/Stream;
      88: invokestatic  #254                // Method java/util/stream/Collectors.toList:()Ljava/util/stream/Collector;
      91: invokeinterface #260,  2          // InterfaceMethod java/util/stream/Stream.collect:(Ljava/util/stream/Collector;)Ljava/lang/Object;
      96: checkcast     #192                // class java/util/List
      99: astore        5
     101: new           #264                // class dev/langchain4j/store/embedding/EmbeddingSearchResult
     104: dup
     105: aload         5
     107: invokespecial #266                // Method dev/langchain4j/store/embedding/EmbeddingSearchResult."<init>":(Ljava/util/List;)V
     110: areturn

  private void addInternal(java.lang.String, dev.langchain4j.data.embedding.Embedding, dev.langchain4j.data.segment.TextSegment);
    Code:
       0: aload_0
       1: aload_1
       2: invokestatic  #269                // Method java/util/Collections.singletonList:(Ljava/lang/Object;)Ljava/util/List;
       5: aload_2
       6: invokestatic  #269                // Method java/util/Collections.singletonList:(Ljava/lang/Object;)Ljava/util/List;
       9: aload_3
      10: ifnonnull     17
      13: aconst_null
      14: goto          21
      17: aload_3
      18: invokestatic  #269                // Method java/util/Collections.singletonList:(Ljava/lang/Object;)Ljava/util/List;
      21: invokevirtual #202                // Method addAll:(Ljava/util/List;Ljava/util/List;Ljava/util/List;)V
      24: return

  public void addAll(java.util.List<java.lang.String>, java.util.List<dev.langchain4j.data.embedding.Embedding>, java.util.List<dev.langchain4j.data.segment.TextSegment>);
    Code:
       0: aload_1
       1: invokestatic  #275                // Method dev/langchain4j/internal/Utils.isNullOrEmpty:(Ljava/util/Collection;)Z
       4: ifne          21
       7: aload_1
       8: invokestatic  #275                // Method dev/langchain4j/internal/Utils.isNullOrEmpty:(Ljava/util/Collection;)Z
      11: ifne          21
      14: aload_2
      15: invokestatic  #275                // Method dev/langchain4j/internal/Utils.isNullOrEmpty:(Ljava/util/Collection;)Z
      18: ifeq          22
      21: return
      22: new           #279                // class java/util/ArrayList
      25: dup
      26: invokespecial #281                // Method java/util/ArrayList."<init>":()V
      29: astore        4
      31: aload         4
      33: new           #282                // class io/milvus/param/dml/InsertParam$Field
      36: dup
      37: aload_0
      38: getfield      #91                 // Field fieldDefinition:Ldev/langchain4j/store/embedding/milvus/FieldDefinition;
      41: invokevirtual #284                // Method dev/langchain4j/store/embedding/milvus/FieldDefinition.getIdFieldName:()Ljava/lang/String;
      44: aload_1
      45: invokespecial #287                // Method io/milvus/param/dml/InsertParam$Field."<init>":(Ljava/lang/String;Ljava/util/List;)V
      48: invokeinterface #290,  2          // InterfaceMethod java/util/List.add:(Ljava/lang/Object;)Z
      53: pop
      54: aload         4
      56: new           #282                // class io/milvus/param/dml/InsertParam$Field
      59: dup
      60: aload_0
      61: getfield      #91                 // Field fieldDefinition:Ldev/langchain4j/store/embedding/milvus/FieldDefinition;
      64: invokevirtual #293                // Method dev/langchain4j/store/embedding/milvus/FieldDefinition.getTextFieldName:()Ljava/lang/String;
      67: aload_3
      68: aload_1
      69: invokeinterface #191,  1          // InterfaceMethod java/util/List.size:()I
      74: invokestatic  #296                // Method dev/langchain4j/store/embedding/milvus/Mapper.toScalars:(Ljava/util/List;I)Ljava/util/List;
      77: invokespecial #287                // Method io/milvus/param/dml/InsertParam$Field."<init>":(Ljava/lang/String;Ljava/util/List;)V
      80: invokeinterface #290,  2          // InterfaceMethod java/util/List.add:(Ljava/lang/Object;)Z
      85: pop
      86: aload         4
      88: new           #282                // class io/milvus/param/dml/InsertParam$Field
      91: dup
      92: aload_0
      93: getfield      #91                 // Field fieldDefinition:Ldev/langchain4j/store/embedding/milvus/FieldDefinition;
      96: invokevirtual #300                // Method dev/langchain4j/store/embedding/milvus/FieldDefinition.getMetadataFieldName:()Ljava/lang/String;
      99: aload_3
     100: aload_1
     101: invokeinterface #191,  1          // InterfaceMethod java/util/List.size:()I
     106: invokestatic  #303                // Method dev/langchain4j/store/embedding/milvus/Mapper.toMetadataJsons:(Ljava/util/List;I)Ljava/util/List;
     109: invokespecial #287                // Method io/milvus/param/dml/InsertParam$Field."<init>":(Ljava/lang/String;Ljava/util/List;)V
     112: invokeinterface #290,  2          // InterfaceMethod java/util/List.add:(Ljava/lang/Object;)Z
     117: pop
     118: aload         4
     120: new           #282                // class io/milvus/param/dml/InsertParam$Field
     123: dup
     124: aload_0
     125: getfield      #91                 // Field fieldDefinition:Ldev/langchain4j/store/embedding/milvus/FieldDefinition;
     128: invokevirtual #113                // Method dev/langchain4j/store/embedding/milvus/FieldDefinition.getVectorFieldName:()Ljava/lang/String;
     131: aload_2
     132: invokestatic  #306                // Method dev/langchain4j/store/embedding/milvus/Mapper.toVectors:(Ljava/util/List;)Ljava/util/List;
     135: invokespecial #287                // Method io/milvus/param/dml/InsertParam$Field."<init>":(Ljava/lang/String;Ljava/util/List;)V
     138: invokeinterface #290,  2          // InterfaceMethod java/util/List.add:(Ljava/lang/Object;)Z
     143: pop
     144: aload_0
     145: getfield      #26                 // Field milvusClient:Lio/milvus/client/MilvusServiceClient;
     148: aload_0
     149: getfield      #39                 // Field collectionName:Ljava/lang/String;
     152: aload         4
     154: invokestatic  #310                // Method dev/langchain4j/store/embedding/milvus/CollectionOperationsExecutor.insert:(Lio/milvus/client/MilvusServiceClient;Ljava/lang/String;Ljava/util/List;)V
     157: aload_0
     158: getfield      #75                 // Field autoFlushOnInsert:Z
     161: ifeq          175
     164: aload_0
     165: getfield      #26                 // Field milvusClient:Lio/milvus/client/MilvusServiceClient;
     168: aload_0
     169: getfield      #39                 // Field collectionName:Ljava/lang/String;
     172: invokestatic  #314                // Method dev/langchain4j/store/embedding/milvus/CollectionOperationsExecutor.flush:(Lio/milvus/client/MilvusServiceClient;Ljava/lang/String;)V
     175: return

  public void removeAll(java.util.Collection<java.lang.String>);
    Code:
       0: aload_1
       1: ldc_w         #317                // String ids
       4: invokestatic  #319                // Method dev/langchain4j/internal/ValidationUtils.ensureNotEmpty:(Ljava/util/Collection;Ljava/lang/String;)Ljava/util/Collection;
       7: pop
       8: aload_0
       9: getfield      #26                 // Field milvusClient:Lio/milvus/client/MilvusServiceClient;
      12: aload_0
      13: getfield      #39                 // Field collectionName:Ljava/lang/String;
      16: ldc_w         #323                // String %s in %s
      19: iconst_2
      20: anewarray     #12                 // class java/lang/Object
      23: dup
      24: iconst_0
      25: aload_0
      26: getfield      #91                 // Field fieldDefinition:Ldev/langchain4j/store/embedding/milvus/FieldDefinition;
      29: invokevirtual #284                // Method dev/langchain4j/store/embedding/milvus/FieldDefinition.getIdFieldName:()Ljava/lang/String;
      32: aastore
      33: dup
      34: iconst_1
      35: aload_1
      36: invokestatic  #325                // Method dev/langchain4j/store/embedding/milvus/MilvusMetadataFilterMapper.formatValues:(Ljava/util/Collection;)Ljava/util/List;
      39: aastore
      40: invokestatic  #331                // Method java/lang/String.format:(Ljava/lang/String;[Ljava/lang/Object;)Ljava/lang/String;
      43: invokestatic  #335                // Method dev/langchain4j/store/embedding/milvus/CollectionOperationsExecutor.removeForVector:(Lio/milvus/client/MilvusServiceClient;Ljava/lang/String;Ljava/lang/String;)V
      46: return

  public void removeAll(dev.langchain4j.store.embedding.filter.Filter);
    Code:
       0: aload_1
       1: ldc_w         #339                // String filter
       4: invokestatic  #18                 // Method dev/langchain4j/internal/ValidationUtils.ensureNotNull:(Ljava/lang/Object;Ljava/lang/String;)Ljava/lang/Object;
       7: pop
       8: aload_0
       9: getfield      #26                 // Field milvusClient:Lio/milvus/client/MilvusServiceClient;
      12: aload_0
      13: getfield      #39                 // Field collectionName:Ljava/lang/String;
      16: aload_1
      17: aload_0
      18: getfield      #91                 // Field fieldDefinition:Ldev/langchain4j/store/embedding/milvus/FieldDefinition;
      21: invokevirtual #300                // Method dev/langchain4j/store/embedding/milvus/FieldDefinition.getMetadataFieldName:()Ljava/lang/String;
      24: invokestatic  #340                // Method dev/langchain4j/store/embedding/milvus/MilvusMetadataFilterMapper.map:(Ldev/langchain4j/store/embedding/filter/Filter;Ljava/lang/String;)Ljava/lang/String;
      27: invokestatic  #335                // Method dev/langchain4j/store/embedding/milvus/CollectionOperationsExecutor.removeForVector:(Lio/milvus/client/MilvusServiceClient;Ljava/lang/String;Ljava/lang/String;)V
      30: return

  public void removeAll();
    Code:
       0: aload_0
       1: getfield      #26                 // Field milvusClient:Lio/milvus/client/MilvusServiceClient;
       4: aload_0
       5: getfield      #39                 // Field collectionName:Ljava/lang/String;
       8: ldc_w         #344                // String %s != \"\"
      11: iconst_1
      12: anewarray     #12                 // class java/lang/Object
      15: dup
      16: iconst_0
      17: aload_0
      18: getfield      #91                 // Field fieldDefinition:Ldev/langchain4j/store/embedding/milvus/FieldDefinition;
      21: invokevirtual #284                // Method dev/langchain4j/store/embedding/milvus/FieldDefinition.getIdFieldName:()Ljava/lang/String;
      24: aastore
      25: invokestatic  #331                // Method java/lang/String.format:(Ljava/lang/String;[Ljava/lang/Object;)Ljava/lang/String;
      28: invokestatic  #335                // Method dev/langchain4j/store/embedding/milvus/CollectionOperationsExecutor.removeForVector:(Lio/milvus/client/MilvusServiceClient;Ljava/lang/String;Ljava/lang/String;)V
      31: return

  public java.lang.String add(dev.langchain4j.data.embedding.Embedding, java.lang.Object);
    Code:
       0: aload_0
       1: aload_1
       2: aload_2
       3: checkcast     #346                // class dev/langchain4j/data/segment/TextSegment
       6: invokevirtual #348                // Method add:(Ldev/langchain4j/data/embedding/Embedding;Ldev/langchain4j/data/segment/TextSegment;)Ljava/lang/String;
       9: areturn

  private static boolean lambda$search$0(dev.langchain4j.store.embedding.EmbeddingSearchRequest, dev.langchain4j.store.embedding.EmbeddingMatch);
    Code:
       0: aload_1
       1: invokevirtual #351                // Method dev/langchain4j/store/embedding/EmbeddingMatch.score:()Ljava/lang/Double;
       4: invokevirtual #357                // Method java/lang/Double.doubleValue:()D
       7: aload_0
       8: invokevirtual #363                // Method dev/langchain4j/store/embedding/EmbeddingSearchRequest.minScore:()D
      11: dcmpl
      12: iflt          19
      15: iconst_1
      16: goto          20
      19: iconst_0
      20: ireturn
}
