Compiled from "MessageWindowChatMemory.java"
public class dev.langchain4j.memory.chat.MessageWindowChatMemory implements dev.langchain4j.memory.ChatMemory {
  private static final org.slf4j.Logger log;

  private final java.lang.Object id;

  private final java.lang.Integer maxMessages;

  private final dev.langchain4j.store.memory.chat.ChatMemoryStore store;

  private dev.langchain4j.memory.chat.MessageWindowChatMemory(dev.langchain4j.memory.chat.MessageWindowChatMemory$Builder);
    Code:
       0: aload_0
       1: invokespecial #1                  // Method java/lang/Object."<init>":()V
       4: aload_0
       5: aload_1
       6: getfield      #7                  // Field dev/langchain4j/memory/chat/MessageWindowChatMemory$Builder.id:Ljava/lang/Object;
       9: ldc           #13                 // String id
      11: invokestatic  #14                 // Method dev/langchain4j/internal/ValidationUtils.ensureNotNull:(Ljava/lang/Object;Ljava/lang/String;)Ljava/lang/Object;
      14: putfield      #20                 // Field id:Ljava/lang/Object;
      17: aload_0
      18: aload_1
      19: getfield      #23                 // Field dev/langchain4j/memory/chat/MessageWindowChatMemory$Builder.maxMessages:Ljava/lang/Integer;
      22: ldc           #27                 // String maxMessages
      24: invokestatic  #28                 // Method dev/langchain4j/internal/ValidationUtils.ensureGreaterThanZero:(Ljava/lang/Integer;Ljava/lang/String;)I
      27: invokestatic  #32                 // Method java/lang/Integer.valueOf:(I)Ljava/lang/Integer;
      30: putfield      #38                 // Field maxMessages:Ljava/lang/Integer;
      33: aload_0
      34: aload_1
      35: invokevirtual #39                 // Method dev/langchain4j/memory/chat/MessageWindowChatMemory$Builder.store:()Ldev/langchain4j/store/memory/chat/ChatMemoryStore;
      38: ldc           #43                 // String store
      40: invokestatic  #14                 // Method dev/langchain4j/internal/ValidationUtils.ensureNotNull:(Ljava/lang/Object;Ljava/lang/String;)Ljava/lang/Object;
      43: checkcast     #44                 // class dev/langchain4j/store/memory/chat/ChatMemoryStore
      46: putfield      #46                 // Field store:Ldev/langchain4j/store/memory/chat/ChatMemoryStore;
      49: return

  public java.lang.Object id();
    Code:
       0: aload_0
       1: getfield      #20                 // Field id:Ljava/lang/Object;
       4: areturn

  public void add(dev.langchain4j.data.message.ChatMessage);
    Code:
       0: aload_0
       1: invokevirtual #49                 // Method messages:()Ljava/util/List;
       4: astore_2
       5: aload_1
       6: instanceof    #53                 // class dev/langchain4j/data/message/SystemMessage
       9: ifeq          50
      12: aload_2
      13: invokestatic  #55                 // Method findSystemMessage:(Ljava/util/List;)Ljava/util/Optional;
      16: astore_3
      17: aload_3
      18: invokevirtual #59                 // Method java/util/Optional.isPresent:()Z
      21: ifeq          50
      24: aload_3
      25: invokevirtual #65                 // Method java/util/Optional.get:()Ljava/lang/Object;
      28: checkcast     #53                 // class dev/langchain4j/data/message/SystemMessage
      31: aload_1
      32: invokevirtual #69                 // Method dev/langchain4j/data/message/SystemMessage.equals:(Ljava/lang/Object;)Z
      35: ifeq          39
      38: return
      39: aload_2
      40: aload_3
      41: invokevirtual #65                 // Method java/util/Optional.get:()Ljava/lang/Object;
      44: invokeinterface #73,  2           // InterfaceMethod java/util/List.remove:(Ljava/lang/Object;)Z
      49: pop
      50: aload_2
      51: aload_1
      52: invokeinterface #78,  2           // InterfaceMethod java/util/List.add:(Ljava/lang/Object;)Z
      57: pop
      58: aload_2
      59: aload_0
      60: getfield      #38                 // Field maxMessages:Ljava/lang/Integer;
      63: invokevirtual #81                 // Method java/lang/Integer.intValue:()I
      66: invokestatic  #85                 // Method ensureCapacity:(Ljava/util/List;I)V
      69: aload_0
      70: getfield      #46                 // Field store:Ldev/langchain4j/store/memory/chat/ChatMemoryStore;
      73: aload_0
      74: getfield      #20                 // Field id:Ljava/lang/Object;
      77: aload_2
      78: invokeinterface #89,  3           // InterfaceMethod dev/langchain4j/store/memory/chat/ChatMemoryStore.updateMessages:(Ljava/lang/Object;Ljava/util/List;)V
      83: return

  private static java.util.Optional<dev.langchain4j.data.message.SystemMessage> findSystemMessage(java.util.List<dev.langchain4j.data.message.ChatMessage>);
    Code:
       0: aload_0
       1: invokeinterface #93,  1           // InterfaceMethod java/util/List.stream:()Ljava/util/stream/Stream;
       6: invokedynamic #97,  0             // InvokeDynamic #0:test:()Ljava/util/function/Predicate;
      11: invokeinterface #101,  2          // InterfaceMethod java/util/stream/Stream.filter:(Ljava/util/function/Predicate;)Ljava/util/stream/Stream;
      16: invokedynamic #107,  0            // InvokeDynamic #1:apply:()Ljava/util/function/Function;
      21: invokeinterface #111,  2          // InterfaceMethod java/util/stream/Stream.map:(Ljava/util/function/Function;)Ljava/util/stream/Stream;
      26: invokeinterface #115,  1          // InterfaceMethod java/util/stream/Stream.findAny:()Ljava/util/Optional;
      31: areturn

  public java.util.List<dev.langchain4j.data.message.ChatMessage> messages();
    Code:
       0: new           #119                // class java/util/LinkedList
       3: dup
       4: aload_0
       5: getfield      #46                 // Field store:Ldev/langchain4j/store/memory/chat/ChatMemoryStore;
       8: aload_0
       9: getfield      #20                 // Field id:Ljava/lang/Object;
      12: invokeinterface #121,  2          // InterfaceMethod dev/langchain4j/store/memory/chat/ChatMemoryStore.getMessages:(Ljava/lang/Object;)Ljava/util/List;
      17: invokespecial #125                // Method java/util/LinkedList."<init>":(Ljava/util/Collection;)V
      20: astore_1
      21: aload_1
      22: aload_0
      23: getfield      #38                 // Field maxMessages:Ljava/lang/Integer;
      26: invokevirtual #81                 // Method java/lang/Integer.intValue:()I
      29: invokestatic  #85                 // Method ensureCapacity:(Ljava/util/List;I)V
      32: aload_1
      33: areturn

  private static void ensureCapacity(java.util.List<dev.langchain4j.data.message.ChatMessage>, int);
    Code:
       0: aload_0
       1: invokeinterface #128,  1          // InterfaceMethod java/util/List.size:()I
       6: iload_1
       7: if_icmple     119
      10: iconst_0
      11: istore_2
      12: aload_0
      13: iconst_0
      14: invokeinterface #131,  2          // InterfaceMethod java/util/List.get:(I)Ljava/lang/Object;
      19: instanceof    #53                 // class dev/langchain4j/data/message/SystemMessage
      22: ifeq          27
      25: iconst_1
      26: istore_2
      27: aload_0
      28: iload_2
      29: invokeinterface #134,  2          // InterfaceMethod java/util/List.remove:(I)Ljava/lang/Object;
      34: checkcast     #136                // class dev/langchain4j/data/message/ChatMessage
      37: astore_3
      38: getstatic     #138                // Field log:Lorg/slf4j/Logger;
      41: ldc           #142                // String Evicting the following message to comply with the capacity requirement: {}
      43: aload_3
      44: invokeinterface #144,  3          // InterfaceMethod org/slf4j/Logger.trace:(Ljava/lang/String;Ljava/lang/Object;)V
      49: aload_3
      50: instanceof    #150                // class dev/langchain4j/data/message/AiMessage
      53: ifeq          116
      56: aload_3
      57: checkcast     #150                // class dev/langchain4j/data/message/AiMessage
      60: invokevirtual #152                // Method dev/langchain4j/data/message/AiMessage.hasToolExecutionRequests:()Z
      63: ifeq          116
      66: aload_0
      67: invokeinterface #128,  1          // InterfaceMethod java/util/List.size:()I
      72: iload_2
      73: if_icmple     116
      76: aload_0
      77: iload_2
      78: invokeinterface #131,  2          // InterfaceMethod java/util/List.get:(I)Ljava/lang/Object;
      83: instanceof    #155                // class dev/langchain4j/data/message/ToolExecutionResultMessage
      86: ifeq          116
      89: aload_0
      90: iload_2
      91: invokeinterface #134,  2          // InterfaceMethod java/util/List.remove:(I)Ljava/lang/Object;
      96: checkcast     #136                // class dev/langchain4j/data/message/ChatMessage
      99: astore        4
     101: getstatic     #138                // Field log:Lorg/slf4j/Logger;
     104: ldc           #157                // String Evicting orphan {}
     106: aload         4
     108: invokeinterface #144,  3          // InterfaceMethod org/slf4j/Logger.trace:(Ljava/lang/String;Ljava/lang/Object;)V
     113: goto          66
     116: goto          0
     119: return

  public void clear();
    Code:
       0: aload_0
       1: getfield      #46                 // Field store:Ldev/langchain4j/store/memory/chat/ChatMemoryStore;
       4: aload_0
       5: getfield      #20                 // Field id:Ljava/lang/Object;
       8: invokeinterface #159,  2          // InterfaceMethod dev/langchain4j/store/memory/chat/ChatMemoryStore.deleteMessages:(Ljava/lang/Object;)V
      13: return

  public static dev.langchain4j.memory.chat.MessageWindowChatMemory$Builder builder();
    Code:
       0: new           #8                  // class dev/langchain4j/memory/chat/MessageWindowChatMemory$Builder
       3: dup
       4: invokespecial #163                // Method dev/langchain4j/memory/chat/MessageWindowChatMemory$Builder."<init>":()V
       7: areturn

  public static dev.langchain4j.memory.chat.MessageWindowChatMemory withMaxMessages(int);
    Code:
       0: invokestatic  #164                // Method builder:()Ldev/langchain4j/memory/chat/MessageWindowChatMemory$Builder;
       3: iload_0
       4: invokestatic  #32                 // Method java/lang/Integer.valueOf:(I)Ljava/lang/Integer;
       7: invokevirtual #168                // Method dev/langchain4j/memory/chat/MessageWindowChatMemory$Builder.maxMessages:(Ljava/lang/Integer;)Ldev/langchain4j/memory/chat/MessageWindowChatMemory$Builder;
      10: invokevirtual #171                // Method dev/langchain4j/memory/chat/MessageWindowChatMemory$Builder.build:()Ldev/langchain4j/memory/chat/MessageWindowChatMemory;
      13: areturn

  private static dev.langchain4j.data.message.SystemMessage lambda$findSystemMessage$1(dev.langchain4j.data.message.ChatMessage);
    Code:
       0: aload_0
       1: checkcast     #53                 // class dev/langchain4j/data/message/SystemMessage
       4: areturn

  private static boolean lambda$findSystemMessage$0(dev.langchain4j.data.message.ChatMessage);
    Code:
       0: aload_0
       1: instanceof    #53                 // class dev/langchain4j/data/message/SystemMessage
       4: ireturn

  static {};
    Code:
       0: ldc           #21                 // class dev/langchain4j/memory/chat/MessageWindowChatMemory
       2: invokestatic  #175                // Method org/slf4j/LoggerFactory.getLogger:(Ljava/lang/Class;)Lorg/slf4j/Logger;
       5: putstatic     #138                // Field log:Lorg/slf4j/Logger;
       8: return
}
