Compiled from "MessageWindowChatMemory.java"
public class dev.langchain4j.memory.chat.MessageWindowChatMemory$Builder {
  private java.lang.Object id;

  private java.lang.Integer maxMessages;

  private dev.langchain4j.store.memory.chat.ChatMemoryStore store;

  public dev.langchain4j.memory.chat.MessageWindowChatMemory$Builder();
    Code:
       0: aload_0
       1: invokespecial #1                  // Method java/lang/Object."<init>":()V
       4: aload_0
       5: ldc           #9                  // String default
       7: putfield      #11                 // Field id:Ljava/lang/Object;
      10: return

  public dev.langchain4j.memory.chat.MessageWindowChatMemory$Builder id(java.lang.Object);
    Code:
       0: aload_0
       1: aload_1
       2: putfield      #11                 // Field id:Ljava/lang/Object;
       5: aload_0
       6: areturn

  public dev.langchain4j.memory.chat.MessageWindowChatMemory$Builder maxMessages(java.lang.Integer);
    Code:
       0: aload_0
       1: aload_1
       2: putfield      #17                 // Field maxMessages:Ljava/lang/Integer;
       5: aload_0
       6: areturn

  public dev.langchain4j.memory.chat.MessageWindowChatMemory$Builder chatMemoryStore(dev.langchain4j.store.memory.chat.ChatMemoryStore);
    Code:
       0: aload_0
       1: aload_1
       2: putfield      #21                 // Field store:Ldev/langchain4j/store/memory/chat/ChatMemoryStore;
       5: aload_0
       6: areturn

  public dev.langchain4j.memory.chat.MessageWindowChatMemory build();
    Code:
       0: new           #25                 // class dev/langchain4j/memory/chat/MessageWindowChatMemory
       3: dup
       4: aload_0
       5: invokespecial #27                 // Method dev/langchain4j/memory/chat/MessageWindowChatMemory."<init>":(Ldev/langchain4j/memory/chat/MessageWindowChatMemory$Builder;)V
       8: areturn

  public dev.langchain4j.store.memory.chat.ChatMemoryStore store();
    Code:
       0: aload_0
       1: getfield      #21                 // Field store:Ldev/langchain4j/store/memory/chat/ChatMemoryStore;
       4: ifnull        14
       7: aload_0
       8: getfield      #21                 // Field store:Ldev/langchain4j/store/memory/chat/ChatMemoryStore;
      11: goto          25
      14: new           #30                 // class dev/langchain4j/memory/chat/SingleSlotChatMemoryStore
      17: dup
      18: aload_0
      19: getfield      #11                 // Field id:Ljava/lang/Object;
      22: invokespecial #32                 // Method dev/langchain4j/memory/chat/SingleSlotChatMemoryStore."<init>":(Ljava/lang/Object;)V
      25: areturn
}
